changelog.md
sportorg/__init__.py
sportorg/common/__init__.py
sportorg/common/audio.py
sportorg/common/broker.py
sportorg/common/fake_std.py
sportorg/common/final.py
sportorg/common/model.py
sportorg/common/otime.py
sportorg/common/scripts.py
sportorg/common/singleton.py
sportorg/common/template.py
sportorg/common/version.py
sportorg/config.py
sportorg/gui/__init__.py
sportorg/gui/dialogs/__init__.py
sportorg/gui/dialogs/about.py
sportorg/gui/dialogs/bib_dialog.py
sportorg/gui/dialogs/course_edit.py
sportorg/gui/dialogs/cp_delete.py
sportorg/gui/dialogs/dialog.py
sportorg/gui/dialogs/entry_filter.py
sportorg/gui/dialogs/entry_mass_edit.py
sportorg/gui/dialogs/event_properties.py
sportorg/gui/dialogs/file_dialog.py
sportorg/gui/dialogs/group_edit.py
sportorg/gui/dialogs/group_ranking.py
sportorg/gui/dialogs/live_dialog.py
sportorg/gui/dialogs/not_start_dialog.py
sportorg/gui/dialogs/number_change.py
sportorg/gui/dialogs/organization_edit.py
sportorg/gui/dialogs/person_edit.py
sportorg/gui/dialogs/print_properties.py
sportorg/gui/dialogs/relay_clone_dialog.py
sportorg/gui/dialogs/relay_number_dialog.py
sportorg/gui/dialogs/rent_cards_dialog.py
sportorg/gui/dialogs/report_dialog.py
sportorg/gui/dialogs/result_edit.py
sportorg/gui/dialogs/scores_dialog.py
sportorg/gui/dialogs/search_dialog.py
sportorg/gui/dialogs/settings.py
sportorg/gui/dialogs/sportorg_import_dialog.py
sportorg/gui/dialogs/start_handicap_dialog.py
sportorg/gui/dialogs/start_preparation.py
sportorg/gui/dialogs/start_time_change_dialog.py
sportorg/gui/dialogs/teamwork_properties.py
sportorg/gui/dialogs/telegram_dialog.py
sportorg/gui/dialogs/text_io.py
sportorg/gui/dialogs/timekeeping_properties.py
sportorg/gui/global_access.py
sportorg/gui/main.py
sportorg/gui/main_window.py
sportorg/gui/menu/__init__.py
sportorg/gui/menu/action.py
sportorg/gui/menu/actions.py
sportorg/gui/menu/factory.py
sportorg/gui/menu/menu.py
sportorg/gui/tabs/__init__.py
sportorg/gui/tabs/courses.py
sportorg/gui/tabs/groups.py
sportorg-1.4.0.dist-info/LICENSE
sportorg-1.4.0.dist-info/WHEEL
sportorg-1.4.0.dist-info/METADATA
sportorg-1.4.0.dist-info/RECORD
